{
  "url": "https://linkedin.com/company/github",
  "data": {
    "content": "GitHub Software Development San Francisco, CA 5,211,444 followers The AI-powered developer platform to build, scale, and deliver secure software. See   View all 5,561 employees Industry Software Development Company size 501-1,000 employees Headquarters San Francisco, CA Type Privately Held Founded 2008 Products GitHub GitHub Actions GitHub Advanced Security, Static Application Security Testing (SAST) Software GitHub Advanced Security Static Application Security Testing (SAST) Software GitHub Codespaces GitHub Copilot GitHub Enterprise GitHub Issues, Project Management Software GitHub Issues Project Management Software Locations Primary 88 Colin P Kelly Jr St San Francisco, CA 94107, US Get directions Employees at GitHub Edd Wilder-James TPM Director for Copilot, Platform at GitHub | AI, developer tooling, security Bradley Dunn Helping Developers and Companies Build Better Software Faster at GitHub Clay Nelson WW Industry Solutions Strategy Lead @ GitHub | Enterprise Software, Agile Methodologies Jens Hilligs√∏e See all employees Updates GitHub 5,211,444 followers 14h Edited Surprise! Early bird pricing for #GitHubUniverse is now extended to Sept 17 üôå Don't miss your last chance to save $400 on your ticket üéüÔ∏è https://lnkd.in/gATenRQj GitHub 5,211,444 followers 19h What happens when AI writes 90% of code? üòÆ Here‚Äôs how to keep up and stand out ü•á üåç The developer role is changing. Here's how to stay ahead. GitHub on  GitHub 5,211,444 followers 21h It's not one size fits all, it's one size fits . Is that the future of software? Our latest GitHub Podcast episode talks building tools and getting personal. Listen to it now üëâ https://gh.io/podcast or wherever you listen to podcasts. GitHub reposted this Visual Studio Code 80,537 followers 1d New VS Code release is dropping this week - wondering how you can catch up on the latest? Tune into the release livestream this Thursday! You'll see demos directly from the VS Code and GitHub product teams, as well as special guests: https://lnkd.in/gmcHwgqU VS Code Live - v1.104 Release https://www.youtube.com/ GitHub 5,211,444 followers 1d Leave the bugs for GitHub Copilot to fix. ü§ñ Assign an issue to GitHub Copilot coding agent, and it will write the code and create a pull request for you. ‚úÖ So spend less time on small tasks and more time building. Here's how it works. ‚¨áÔ∏è https://lnkd.in/gbJDWu5T About GitHub Copilot coding agent - GitHub Docs GitHub 5,211,444 followers 2d When you're a maintainer, you can lose a lot of time on project admin. ‚è∞ With GitHub Models, you can use AI to automate the tedious stuff : ‚Ä¢ Closing duplicate issues ‚Ä¢ Asking for reproduction steps ‚Ä¢ Labeling pull requests Leave the busywork to AI and shift your focus to what matters most. ‚¨áÔ∏è https://lnkd.in/gzRcP9dQ How GitHub Models can help open source maintainers focus on what matters https://github.blog GitHub 5,211,444 followers 3d What's the latest with React Native? Reanimated 4 brings a more declarative, CSS-style approach to animations and transitions. ‚ú® We break down what you can do with this new API. ‚ñ∂Ô∏è GitHub 5,211,444 followers 3d We used AI to help our AI find secrets. üëÄ Here's how our Secret Protection team used GitHub Copilot to improve our own secret scanning, closing the gap on less common token types. üîé https://lnkd.in/gJmUsYQ8 How we accelerated Secret Protection engineering with Copilot https://github.blog GitHub 5,211,444 followers 4d Take your AI tools beyond the basics. Start using Model Context Protocol (MCP). üöÄ With MCP, you can  AI assistants  GitHub Copilot to your tools, APIs, and data sources. To show how it works, we built a fun, interactive example: a game server that lets you play Tic-Tac-Toe and Rock, Paper, Scissors against Copilot! ü§ñ Walk through the project (written in TypeScript) and learn how to build your own MCP server from scratch.üëá https://lnkd.in/d9VYK6Kq Building your first MCP server: How to extend AI tools with custom capabilities https://github.blog GitHub 5,211,444 followers 4d AI won‚Äôt take your job, but THIS might üëÄ We chatted with Sajjaad Khader at #GitHubUniverse 2024  to see what you are missing Find people you know at GitHub Browse recommended  for you View all updates, news, and articles  Affiliated pages Microsoft Software Development Redmond, Washington GitHub Brasil Software Development GitHub LATAM Software Development GitHub Education Software Development GitHub Enterprise Software Development GitHub Security Lab Software Development Student Developer Pack Similar pages Microsoft Software Development Redmond, Washington Google Software Development Mountain View, CA GitLab IT Services and IT Consulting San Francisco, California OpenAI Research Services San Francisco, CA W3Schools.com E-Learning Providers Atlassian Software Development Sydney, NSW GeeksforGeeks Education NOIDA, G. B. Nagar, Uttar Pradesh Amazon Software Development Seattle, WA IBM IT Services and IT Consulting Armonk, New York, NY Meta Software Development Menlo Park, CA Browse  Engineer  GitHub  Developer  Software Engineer  Analyst  Senior Software Engineer  Manager  Intern  Scientist  Project Manager  Director  Marketing Manager  Program Manager  Associate  Account Executive  Account Manager  Engineering Manager  Python Developer  Full Stack Engineer  Vice President  Funding GitHub 4 total rounds Last Round Secondary market Jan 21, 2016 External Crunchbase Link for last round of funding See more info on crunchbase",
    "industry": "Software Development",
    "companySize": "501-1,000 employees",
    "headquarters": "San Francisco, CA",
    "founded": "2008",
    "name": "GitHub",
    "description": "GitHub | 5,211,444 followers on LinkedIn. The AI-powered developer platform to build, scale, and deliver secure software. | As the global home for all developers, GitHub is the complete AI-powered developer platform to build, scale, and deliver secure software. Over 100 million people, including developers from 90 of the Fortune 100 companies, use GitHub to build amazing things together across 330+ million repositories. With all the collaborative features of GitHub, it has never been easier for individuals and teams to write faster, better code.",
    "employees": [
      {
        "name": "Edd Wilder-James TPM",
        "title": "Director for Copilot, Platform at GitHub | AI, developer tooling, security",
        "profileUrl": "https://www.linkedin.com/in/wilder-james?trk=org-employees",
        "photoUrl": "https://media.licdn.com/dms/image/v2/C4E03AQEeti6qiowDYg/profile-displayphoto-shrink_100_100/profile-displayphoto-shrink_100_100/0/1516155860319?e=2147483647&v=beta&t=FRcFGza4BxaWXxzVWlBwTGE1i3bcq4rq1U_WhP2yoYg"
      },
      {
        "name": "Bradley Dunn",
        "title": "Helping Developers and Companies Build Better Software Faster at GitHub",
        "profileUrl": "https://www.linkedin.com/in/pbradleydunn?trk=org-employees",
        "photoUrl": "https://media.licdn.com/dms/image/v2/C5603AQEqsnW2lTuj9g/profile-displayphoto-shrink_100_100/profile-displayphoto-shrink_100_100/0/1656714811962?e=2147483647&v=beta&t=ksd6Jb0v6Q372hEzV3wPCDiwTHEFm-C1pNEuCFu58kg"
      },
      {
        "name": "Clay Nelson WW Industry Solutions Strategy",
        "title": "Lead @ GitHub | Enterprise Software, Agile Methodologies",
        "profileUrl": "https://www.linkedin.com/in/claynelson?trk=org-employees",
        "photoUrl": "https://media.licdn.com/dms/image/v2/D4E03AQE78TeamYJ0Qw/profile-displayphoto-scale_100_100/B4EZg.KmuxGYAc-/0/1753389624699?e=2147483647&v=beta&t=waycCdtLPQptfCpfsijE2LCdC1Tiw2d1T4tNVMVEUS4"
      },
      {
        "name": "Jens Hilligs√∏e",
        "title": "",
        "profileUrl": "https://dk.linkedin.com/in/hilli?trk=org-employees",
        "photoUrl": "https://media.licdn.com/dms/image/v2/C4D03AQF2DOZtxx7nng/profile-displayphoto-shrink_100_100/profile-displayphoto-shrink_100_100/0/1589183693779?e=2147483647&v=beta&t=kYN7-oFna-OqrDUQUHXMIhkrdKRd0mmhTxf9N55hU10"
      }
    ],
    "logoUrl": "https://media.licdn.com/dms/image/v2/C560BAQFmuLSyL1nlPA/company-logo_200_200/company-logo_200_200/0/1678231359043/github_logo?e=2147483647&v=beta&t=2RO1zjla4T-YiOqKS50e4sc9n8RAgnUqGqu0mcZp5fU"
  }
}